setup.cfg
setup.py
florestlibrarypythonpremium/florestlibrarypythonpremium.py
florestlibrarypythonpremium/tests.py
florestlibrarypythonpremium.egg-info/PKG-INFO
florestlibrarypythonpremium.egg-info/SOURCES.txt
florestlibrarypythonpremium.egg-info/dependency_links.txt
florestlibrarypythonpremium.egg-info/top_level.txt