Metadata-Version: 1.0
Name: florestlibrarypythonpremium
Version: 0.0.0.3
Summary: Библиотека создана Флорестом, тут дохрена хороших функций. Пользуемся!
Home-page: UNKNOWN
Author: UNKNOWN
Author-email: kirillborisenko985@gmail.com
License: UNKNOWN
Platform: UNKNOWN
